<?xml version="1.0" encoding="UTF-8" standalone="yes"?>
<team>
    <arena>Staples Center</arena>
    <conference>Western</conference>
    <division>Pacific</division>
    <founded>1947</founded>
    <head-coach>
        <coach-age>47</coach-age>
        <coach-name>Frank</coach-name>
        <coach-surname>Vogel</coach-surname>
    </head-coach>
    <location>Los Angeles</location>
    <players>
        <player>
            <height>206</height>
            <player-age>36</player-age>
            <player-name>LeBron</player-name>
            <player-surname>James</player-surname>
            <position>F</position>
            <weight>113</weight>
        </player>
        <player>
            <height>208</height>
            <player-age>27</player-age>
            <player-name>Anthony</player-name>
            <player-surname>Davis</player-surname>
            <position>PF</position>
            <weight>115</weight>
        </player>
        <player>
            <height>196</height>
            <player-age>27</player-age>
            <player-name>Alex</player-name>
            <player-surname>Caruso</player-surname>
            <position>G</position>
            <weight>84</weight>
        </player>
        <player>
            <height>208</height>
            <player-age>23</player-age>
            <player-name>Kostas</player-name>
            <player-surname>Antetekoumpo</player-surname>
            <position>F</position>
            <weight>91</weight>
        </player>
        <player>
            <height>196</height>
            <player-age>28</player-age>
            <player-name>Kentavious</player-name>
            <player-surname>Cardwell-Pope</player-surname>
            <position>G</position>
            <weight>93</weight>
        </player>
        <player>
            <height>198</height>
            <player-age>36</player-age>
            <player-name>Jared</player-name>
            <player-surname>Dudley</player-surname>
            <position>F</position>
            <weight>108</weight>
        </player>
        <player>
            <height>201</height>
            <player-age>27</player-age>
            <player-name>Montrezl</player-name>
            <player-surname>Harrell</player-surname>
            <position>C</position>
            <weight>109</weight>
        </player>
        <player>
            <height>203</height>
            <player-age>25</player-age>
            <player-name>Kyle</player-name>
            <player-surname>Kuzma</player-surname>
            <position>F</position>
            <weight>100</weight>
        </player>
        <player>
            <height>203</height>
            <player-age>32</player-age>
            <player-name>Markieff</player-name>
            <player-surname>Morris</player-surname>
            <position>F</position>
            <weight>111</weight>
        </player>
        <player>
            <height>206</height>
            <player-age>34</player-age>
            <player-name>Marc</player-name>
            <player-surname>Gasol</player-surname>
            <position>C</position>
            <weight>120</weight>
        </player>
    </players>
    <team-colors/>
    <team-name>Lakers</team-name>
    <title-count>18</title-count>
    <website>www.lakers.com</website>
</team>
